fetch_cord/Cycle.py
fetch_cord/Logger.py
fetch_cord/__init__.py
fetch_cord/__main__.py
fetch_cord/args.py
fetch_cord/config.py
fetch_cord/config_schema.json
fetch_cord/cycles.py
fetch_cord/debugger.py
fetch_cord/run_command.py
fetch_cord/run_rpc.py
fetch_cord/update.py
fetch_cord/computer/Computer.py
fetch_cord/computer/Peripheral_interface.py
fetch_cord/computer/__init__.py
fetch_cord/computer/flatpak.py
fetch_cord/computer/resources.py
fetch_cord/computer/cpu/Cpu_amd.py
fetch_cord/computer/cpu/Cpu_intel.py
fetch_cord/computer/cpu/Cpu_interface.py
fetch_cord/computer/cpu/__init__.py
fetch_cord/computer/cpu/get_cpu.py
fetch_cord/computer/gpu/Gpu_amd.py
fetch_cord/computer/gpu/Gpu_intel.py
fetch_cord/computer/gpu/Gpu_interface.py
fetch_cord/computer/gpu/Gpu_nvidia.py
fetch_cord/computer/gpu/__init__.py
fetch_cord/computer/gpu/get_gpu.py
fetch_cord/computer/mobo/__init__.py
fetch_cord/computer/mobo/get_mobo.py
fetch_cord/resources/__init__.py
fetch_cord/resources/default.conf
fetch_cord/resources/fetch_cord.conf
fetch_cord/resources/fetchcord_ids.json
fetch_cord/resources/systemd_service.py
FetchCord-2.7.7.dist-info/LICENSE
FetchCord-2.7.7.dist-info/METADATA
FetchCord-2.7.7.dist-info/WHEEL
FetchCord-2.7.7.dist-info/entry_points.txt
FetchCord-2.7.7.dist-info/top_level.txt
FetchCord-2.7.7.dist-info/RECORD
