Metadata-Version: 2.1
Name: FetchCord
Version: 2.7.7
Summary: grabs information about your Distro and displays it as Discord Rich Presence.
Home-page: https://github.com/MrPotatoBobx/FetchCord
Author: MrPotatoBobx
Author-email: junkahole23@protonmail.com
License: MIT
Keywords: distro,info,discord,fetch
Platform: UNKNOWN
Classifier: License :: OSI Approved :: MIT License
Classifier: Programming Language :: Python :: 3
Classifier: Operating System :: OS Independent
Requires-Python: >=3.6
